{
	"sally"://仙盟
	{
		"default":"仙盟任务艰辛，呼朋引伴互相帮助可事半功倍。",//打开时的默认对话
	        "specialStr"://特定冒泡内容
			[
			    "点击按钮可呼朋引伴共同除妖",
			    "点击按钮马上领取除妖任务"
			],
		"comStr"://随机对话
			[
			    "完成每日仙盟任务，可获得丰厚仙盟贡献以及仙盟资源",
			    "组队可大幅度加快仙盟任务的完成速度",
                "每日完成仙盟任务人数达一定时，仙盟可获额外资源奖励"
			]
	},
	"ringTs"://封魔
	{
		"default":"封印急需修补，找寻同伴同行可事半功倍",//打开时的默认对话
	        "specialStr"://特定冒泡内容
			[
			    "完成即可点亮封印珠，封印珠齐亮可完成该界封印"
			],
		"comStr"://随机对话
			[
			    "三才印裂，群魔作乱，需尽快修补封印，镇压千魔百鬼！",
			    "需完成人界、地界、天界三界任务方能完整修补封印",
                "接取任务的过程中若能偶遇剑仙，还能获得仙尊祝福。"
			]
	},
	"imperTs"://皇榜
	{
		"default":"皇榜任务险阻，呼朋引伴互相帮助可事半功倍。",//打开时的默认对话
	        "specialStr"://特定冒泡内容
			[
			    "黄沙百战穿金甲，不揭皇榜终不还！"
			],
		"comStr"://随机对话
			[
			    "昊天有命，皇王受之。少侠可是来揭皇榜的？",
			    "皇榜数量有限，欲揭从速！",
                "皇榜每10分钟可免费刷新一次，获得更好的榜单"
			]
	}

}