[
	{
		"type":20001,
		"name":"青梅恋",
		"level":0,
		"marryLv":10,
		"addProperty":[],
		"itemCount":1,
		"addPower":0,
		"icon":"S_qingmeilian",
		"descL":"MarrySkillDescL1",
		"descS":"MarrySkillDescS1"
	},
	{
		"type":20001,
		"name":"青梅恋",
		"level":1,
		"marryLv":10,
		"addProperty":[[5,82]],
		"itemCount":3,
		"addPower":82,
		"icon":"S_qingmeilian",
		"descL":"MarrySkillDescL1",
		"descS":"MarrySkillDescS1"
	},
	{
		"type":20001,
		"name":"青梅恋",
		"level":2,
		"marryLv":15,
		"addProperty":[[5,180]],
		"itemCount":6,
		"addPower":98,
		"icon":"S_qingmeilian",
		"descL":"MarrySkillDescL1",
		"descS":"MarrySkillDescS1"
	},
	{
		"type":20001,
		"name":"青梅恋",
		"level":3,
		"marryLv":15,
		"addProperty":[[5,282]],
		"itemCount":10,
		"addPower":103,
		"icon":"S_qingmeilian",
		"descL":"MarrySkillDescL1",
		"descS":"MarrySkillDescS1"
	},
	{
		"type":20001,
		"name":"青梅恋",
		"level":4,
		"marryLv":20,
		"addProperty":[[5,395]],
		"itemCount":17,
		"addPower":113,
		"icon":"S_qingmeilian",
		"descL":"MarrySkillDescL1",
		"descS":"MarrySkillDescS1"
	},
	{
		"type":20001,
		"name":"青梅恋",
		"level":5,
		"marryLv":20,
		"addProperty":[[5,514]],
		"itemCount":24,
		"addPower":119,
		"icon":"S_qingmeilian",
		"descL":"MarrySkillDescL1",
		"descS":"MarrySkillDescS1"
	},
	{
		"type":20001,
		"name":"青梅恋",
		"level":6,
		"marryLv":25,
		"addProperty":[[5,645]],
		"itemCount":33,
		"addPower":131,
		"icon":"S_qingmeilian",
		"descL":"MarrySkillDescL1",
		"descS":"MarrySkillDescS1"
	},
	{
		"type":20001,
		"name":"青梅恋",
		"level":7,
		"marryLv":25,
		"addProperty":[[5,778]],
		"itemCount":42,
		"addPower":132,
		"icon":"S_qingmeilian",
		"descL":"MarrySkillDescL1",
		"descS":"MarrySkillDescS1"
	},
	{
		"type":20001,
		"name":"青梅恋",
		"level":8,
		"marryLv":30,
		"addProperty":[[5,924]],
		"itemCount":54,
		"addPower":146,
		"icon":"S_qingmeilian",
		"descL":"MarrySkillDescL1",
		"descS":"MarrySkillDescS1"
	},
	{
		"type":20001,
		"name":"青梅恋",
		"level":9,
		"marryLv":30,
		"addProperty":[[5,1068]],
		"itemCount":90,
		"addPower":145,
		"icon":"S_qingmeilian",
		"descL":"MarrySkillDescL1",
		"descS":"MarrySkillDescS1"
	},
	{
		"type":20001,
		"name":"青梅恋",
		"level":10,
		"marryLv":35,
		"addProperty":[[5,1228]],
		"itemCount":143,
		"addPower":159,
		"icon":"S_qingmeilian",
		"descL":"MarrySkillDescL1",
		"descS":"MarrySkillDescS1"
	},
	{
		"type":20001,
		"name":"青梅恋",
		"level":11,
		"marryLv":35,
		"addProperty":[[5,1390]],
		"itemCount":208,
		"addPower":162,
		"icon":"S_qingmeilian",
		"descL":"MarrySkillDescL1",
		"descS":"MarrySkillDescS1"
	},
	{
		"type":20001,
		"name":"青梅恋",
		"level":12,
		"marryLv":40,
		"addProperty":[[5,1568]],
		"itemCount":286,
		"addPower":178,
		"icon":"S_qingmeilian",
		"descL":"MarrySkillDescL1",
		"descS":"MarrySkillDescS1"
	},
	{
		"type":20001,
		"name":"青梅恋",
		"level":13,
		"marryLv":40,
		"addProperty":[[5,1748]],
		"itemCount":374,
		"addPower":180,
		"icon":"S_qingmeilian",
		"descL":"MarrySkillDescL1",
		"descS":"MarrySkillDescS1"
	},
	{
		"type":20001,
		"name":"青梅恋",
		"level":14,
		"marryLv":45,
		"addProperty":[[5,1947]],
		"itemCount":473,
		"addPower":199,
		"icon":"S_qingmeilian",
		"descL":"MarrySkillDescL1",
		"descS":"MarrySkillDescS1"
	},
	{
		"type":20001,
		"name":"青梅恋",
		"level":15,
		"marryLv":45,
		"addProperty":[[5,2132]],
		"itemCount":594,
		"addPower":185,
		"icon":"S_qingmeilian",
		"descL":"MarrySkillDescL1",
		"descS":"MarrySkillDescS1"
	},
	{
		"type":20001,
		"name":"青梅恋",
		"level":16,
		"marryLv":50,
		"addProperty":[[5,2336]],
		"itemCount":741,
		"addPower":204,
		"icon":"S_qingmeilian",
		"descL":"MarrySkillDescL1",
		"descS":"MarrySkillDescS1"
	},
	{
		"type":20001,
		"name":"青梅恋",
		"level":17,
		"marryLv":50,
		"addProperty":[[5,2528]],
		"itemCount":902,
		"addPower":192,
		"icon":"S_qingmeilian",
		"descL":"MarrySkillDescL1",
		"descS":"MarrySkillDescS1"
	},
	{
		"type":20001,
		"name":"青梅恋",
		"level":18,
		"marryLv":55,
		"addProperty":[[5,2739]],
		"itemCount":1081,
		"addPower":211,
		"icon":"S_qingmeilian",
		"descL":"MarrySkillDescL1",
		"descS":"MarrySkillDescS1"
	},
	{
		"type":20001,
		"name":"青梅恋",
		"level":19,
		"marryLv":55,
		"addProperty":[[5,2958]],
		"itemCount":1277,
		"addPower":219,
		"icon":"S_qingmeilian",
		"descL":"MarrySkillDescL1",
		"descS":"MarrySkillDescS1"
	},
	{
		"type":20001,
		"name":"青梅恋",
		"level":20,
		"marryLv":0,
		"addProperty":[[5,3200]],
		"itemCount":0,
		"addPower":241,
		"icon":"S_qingmeilian",
		"descL":"MarrySkillDescL1",
		"descS":"MarrySkillDescS1"
	},
	{
		"type":20002,
		"name":"伊人舞",
		"level":0,
		"marryLv":10,
		"addProperty":[],
		"itemCount":2,
		"addPower":0,
		"icon":"S_yirenwu",
		"descL":"MarrySkillDescL2",
		"descS":"MarrySkillDescS2"
	},
	{
		"type":20002,
		"name":"伊人舞",
		"level":1,
		"marryLv":10,
		"addProperty":[[6,92]],
		"itemCount":3,
		"addPower":31,
		"icon":"S_yirenwu",
		"descL":"MarrySkillDescL2",
		"descS":"MarrySkillDescS2"
	},
	{
		"type":20002,
		"name":"伊人舞",
		"level":2,
		"marryLv":15,
		"addProperty":[[6,202]],
		"itemCount":7,
		"addPower":37,
		"icon":"S_yirenwu",
		"descL":"MarrySkillDescL2",
		"descS":"MarrySkillDescS2"
	},
	{
		"type":20002,
		"name":"伊人舞",
		"level":3,
		"marryLv":15,
		"addProperty":[[6,318]],
		"itemCount":11,
		"addPower":38,
		"icon":"S_yirenwu",
		"descL":"MarrySkillDescL2",
		"descS":"MarrySkillDescS2"
	},
	{
		"type":20002,
		"name":"伊人舞",
		"level":4,
		"marryLv":20,
		"addProperty":[[6,445]],
		"itemCount":18,
		"addPower":42,
		"icon":"S_yirenwu",
		"descL":"MarrySkillDescL2",
		"descS":"MarrySkillDescS2"
	},
	{
		"type":20002,
		"name":"伊人舞",
		"level":5,
		"marryLv":20,
		"addProperty":[[6,579]],
		"itemCount":26,
		"addPower":45,
		"icon":"S_yirenwu",
		"descL":"MarrySkillDescL2",
		"descS":"MarrySkillDescS2"
	},
	{
		"type":20002,
		"name":"伊人舞",
		"level":6,
		"marryLv":25,
		"addProperty":[[6,726]],
		"itemCount":35,
		"addPower":49,
		"icon":"S_yirenwu",
		"descL":"MarrySkillDescL2",
		"descS":"MarrySkillDescS2"
	},
	{
		"type":20002,
		"name":"伊人舞",
		"level":7,
		"marryLv":25,
		"addProperty":[[6,875]],
		"itemCount":44,
		"addPower":50,
		"icon":"S_yirenwu",
		"descL":"MarrySkillDescL2",
		"descS":"MarrySkillDescS2"
	},
	{
		"type":20002,
		"name":"伊人舞",
		"level":8,
		"marryLv":30,
		"addProperty":[[6,1039]],
		"itemCount":60,
		"addPower":55,
		"icon":"S_yirenwu",
		"descL":"MarrySkillDescL2",
		"descS":"MarrySkillDescS2"
	},
	{
		"type":20002,
		"name":"伊人舞",
		"level":9,
		"marryLv":30,
		"addProperty":[[6,1202]],
		"itemCount":98,
		"addPower":54,
		"icon":"S_yirenwu",
		"descL":"MarrySkillDescL2",
		"descS":"MarrySkillDescS2"
	},
	{
		"type":20002,
		"name":"伊人舞",
		"level":10,
		"marryLv":35,
		"addProperty":[[6,1381]],
		"itemCount":155,
		"addPower":60,
		"icon":"S_yirenwu",
		"descL":"MarrySkillDescL2",
		"descS":"MarrySkillDescS2"
	},
	{
		"type":20002,
		"name":"伊人舞",
		"level":11,
		"marryLv":35,
		"addProperty":[[6,1564]],
		"itemCount":223,
		"addPower":61,
		"icon":"S_yirenwu",
		"descL":"MarrySkillDescL2",
		"descS":"MarrySkillDescS2"
	},
	{
		"type":20002,
		"name":"伊人舞",
		"level":12,
		"marryLv":40,
		"addProperty":[[6,1764]],
		"itemCount":303,
		"addPower":67,
		"icon":"S_yirenwu",
		"descL":"MarrySkillDescL2",
		"descS":"MarrySkillDescS2"
	},
	{
		"type":20002,
		"name":"伊人舞",
		"level":13,
		"marryLv":40,
		"addProperty":[[6,1967]],
		"itemCount":392,
		"addPower":68,
		"icon":"S_yirenwu",
		"descL":"MarrySkillDescL2",
		"descS":"MarrySkillDescS2"
	},
	{
		"type":20002,
		"name":"伊人舞",
		"level":14,
		"marryLv":45,
		"addProperty":[[6,2190]],
		"itemCount":495,
		"addPower":74,
		"icon":"S_yirenwu",
		"descL":"MarrySkillDescL2",
		"descS":"MarrySkillDescS2"
	},
	{
		"type":20002,
		"name":"伊人舞",
		"level":15,
		"marryLv":45,
		"addProperty":[[6,2399]],
		"itemCount":621,
		"addPower":69,
		"icon":"S_yirenwu",
		"descL":"MarrySkillDescL2",
		"descS":"MarrySkillDescS2"
	},
	{
		"type":20002,
		"name":"伊人舞",
		"level":16,
		"marryLv":50,
		"addProperty":[[6,2628]],
		"itemCount":772,
		"addPower":76,
		"icon":"S_yirenwu",
		"descL":"MarrySkillDescL2",
		"descS":"MarrySkillDescS2"
	},
	{
		"type":20002,
		"name":"伊人舞",
		"level":17,
		"marryLv":50,
		"addProperty":[[6,2844]],
		"itemCount":937,
		"addPower":72,
		"icon":"S_yirenwu",
		"descL":"MarrySkillDescL2",
		"descS":"MarrySkillDescS2"
	},
	{
		"type":20002,
		"name":"伊人舞",
		"level":18,
		"marryLv":55,
		"addProperty":[[6,3082]],
		"itemCount":1119,
		"addPower":79,
		"icon":"S_yirenwu",
		"descL":"MarrySkillDescL2",
		"descS":"MarrySkillDescS2"
	},
	{
		"type":20002,
		"name":"伊人舞",
		"level":19,
		"marryLv":55,
		"addProperty":[[6,3328]],
		"itemCount":1318,
		"addPower":82,
		"icon":"S_yirenwu",
		"descL":"MarrySkillDescL2",
		"descS":"MarrySkillDescS2"
	},
	{
		"type":20002,
		"name":"伊人舞",
		"level":20,
		"marryLv":0,
		"addProperty":[[6,3600]],
		"itemCount":0,
		"addPower":90,
		"icon":"S_yirenwu",
		"descL":"MarrySkillDescL2",
		"descS":"MarrySkillDescS2"
	},
	{
		"type":20003,
		"name":"相思醉",
		"level":0,
		"marryLv":10,
		"addProperty":[],
		"itemCount":2,
		"addPower":0,
		"icon":"S_xiangsizui",
		"descL":"MarrySkillDescL3",
		"descS":"MarrySkillDescS3"
	},
	{
		"type":20003,
		"name":"相思醉",
		"level":1,
		"marryLv":10,
		"addProperty":[[3,943]],
		"itemCount":4,
		"addPower":59,
		"icon":"S_xiangsizui",
		"descL":"MarrySkillDescL3",
		"descS":"MarrySkillDescS3"
	},
	{
		"type":20003,
		"name":"相思醉",
		"level":2,
		"marryLv":15,
		"addProperty":[[3,2075]],
		"itemCount":8,
		"addPower":71,
		"icon":"S_xiangsizui",
		"descL":"MarrySkillDescL3",
		"descS":"MarrySkillDescS3"
	},
	{
		"type":20003,
		"name":"相思醉",
		"level":3,
		"marryLv":15,
		"addProperty":[[3,3254]],
		"itemCount":12,
		"addPower":74,
		"icon":"S_xiangsizui",
		"descL":"MarrySkillDescL3",
		"descS":"MarrySkillDescS3"
	},
	{
		"type":20003,
		"name":"相思醉",
		"level":4,
		"marryLv":20,
		"addProperty":[[3,4551]],
		"itemCount":20,
		"addPower":81,
		"icon":"S_xiangsizui",
		"descL":"MarrySkillDescL3",
		"descS":"MarrySkillDescS3"
	},
	{
		"type":20003,
		"name":"相思醉",
		"level":5,
		"marryLv":20,
		"addProperty":[[3,5920]],
		"itemCount":28,
		"addPower":86,
		"icon":"S_xiangsizui",
		"descL":"MarrySkillDescL3",
		"descS":"MarrySkillDescS3"
	},
	{
		"type":20003,
		"name":"相思醉",
		"level":6,
		"marryLv":25,
		"addProperty":[[3,7427]],
		"itemCount":36,
		"addPower":94,
		"icon":"S_xiangsizui",
		"descL":"MarrySkillDescL3",
		"descS":"MarrySkillDescS3"
	},
	{
		"type":20003,
		"name":"相思醉",
		"level":7,
		"marryLv":25,
		"addProperty":[[3,8951]],
		"itemCount":46,
		"addPower":95,
		"icon":"S_xiangsizui",
		"descL":"MarrySkillDescL3",
		"descS":"MarrySkillDescS3"
	},
	{
		"type":20003,
		"name":"相思醉",
		"level":8,
		"marryLv":30,
		"addProperty":[[3,10626]],
		"itemCount":67,
		"addPower":105,
		"icon":"S_xiangsizui",
		"descL":"MarrySkillDescL3",
		"descS":"MarrySkillDescS3"
	},
	{
		"type":20003,
		"name":"相思醉",
		"level":9,
		"marryLv":30,
		"addProperty":[[3,12292]],
		"itemCount":107,
		"addPower":104,
		"icon":"S_xiangsizui",
		"descL":"MarrySkillDescL3",
		"descS":"MarrySkillDescS3"
	},
	{
		"type":20003,
		"name":"相思醉",
		"level":10,
		"marryLv":35,
		"addProperty":[[3,14124]],
		"itemCount":167,
		"addPower":115,
		"icon":"S_xiangsizui",
		"descL":"MarrySkillDescL3",
		"descS":"MarrySkillDescS3"
	},
	{
		"type":20003,
		"name":"相思醉",
		"level":11,
		"marryLv":35,
		"addProperty":[[3,15987]],
		"itemCount":239,
		"addPower":116,
		"icon":"S_xiangsizui",
		"descL":"MarrySkillDescL3",
		"descS":"MarrySkillDescS3"
	},
	{
		"type":20003,
		"name":"相思醉",
		"level":12,
		"marryLv":40,
		"addProperty":[[3,18037]],
		"itemCount":320,
		"addPower":128,
		"icon":"S_xiangsizui",
		"descL":"MarrySkillDescL3",
		"descS":"MarrySkillDescS3"
	},
	{
		"type":20003,
		"name":"相思醉",
		"level":13,
		"marryLv":40,
		"addProperty":[[3,20112]],
		"itemCount":412,
		"addPower":130,
		"icon":"S_xiangsizui",
		"descL":"MarrySkillDescL3",
		"descS":"MarrySkillDescS3"
	},
	{
		"type":20003,
		"name":"相思醉",
		"level":14,
		"marryLv":45,
		"addProperty":[[3,22395]],
		"itemCount":518,
		"addPower":143,
		"icon":"S_xiangsizui",
		"descL":"MarrySkillDescL3",
		"descS":"MarrySkillDescS3"
	},
	{
		"type":20003,
		"name":"相思醉",
		"level":15,
		"marryLv":45,
		"addProperty":[[3,24525]],
		"itemCount":650,
		"addPower":133,
		"icon":"S_xiangsizui",
		"descL":"MarrySkillDescL3",
		"descS":"MarrySkillDescS3"
	},
	{
		"type":20003,
		"name":"相思醉",
		"level":16,
		"marryLv":50,
		"addProperty":[[3,26867]],
		"itemCount":803,
		"addPower":146,
		"icon":"S_xiangsizui",
		"descL":"MarrySkillDescL3",
		"descS":"MarrySkillDescS3"
	},
	{
		"type":20003,
		"name":"相思醉",
		"level":17,
		"marryLv":50,
		"addProperty":[[3,29077]],
		"itemCount":972,
		"addPower":138,
		"icon":"S_xiangsizui",
		"descL":"MarrySkillDescL3",
		"descS":"MarrySkillDescS3"
	},
	{
		"type":20003,
		"name":"相思醉",
		"level":18,
		"marryLv":55,
		"addProperty":[[3,31508]],
		"itemCount":1157,
		"addPower":152,
		"icon":"S_xiangsizui",
		"descL":"MarrySkillDescL3",
		"descS":"MarrySkillDescS3"
	},
	{
		"type":20003,
		"name":"相思醉",
		"level":19,
		"marryLv":55,
		"addProperty":[[3,34028]],
		"itemCount":1360,
		"addPower":157,
		"icon":"S_xiangsizui",
		"descL":"MarrySkillDescL3",
		"descS":"MarrySkillDescS3"
	},
	{
		"type":20003,
		"name":"相思醉",
		"level":20,
		"marryLv":0,
		"addProperty":[[3,36800]],
		"itemCount":0,
		"addPower":173,
		"icon":"S_xiangsizui",
		"descL":"MarrySkillDescL3",
		"descS":"MarrySkillDescS3"
	},
	{
		"type":20004,
		"name":"凤求凰",
		"level":0,
		"marryLv":10,
		"addProperty":[],
		"itemCount":2,
		"addPower":0,
		"icon":"S_fengqiuhuang",
		"descL":"MarrySkillDescL4",
		"descS":"MarrySkillDescS4"
	},
	{
		"type":20004,
		"name":"凤求凰",
		"level":1,
		"marryLv":10,
		"addProperty":[[10,25],[16,51],[15,76]],
		"itemCount":4,
		"addPower":95,
		"icon":"S_fengqiuhuang",
		"descL":"MarrySkillDescL4",
		"descS":"MarrySkillDescS4"
	},
	{
		"type":20004,
		"name":"凤求凰",
		"level":2,
		"marryLv":15,
		"addProperty":[[10,56],[16,112],[15,169]],
		"itemCount":9,
		"addPower":114,
		"icon":"S_fengqiuhuang",
		"descL":"MarrySkillDescL4",
		"descS":"MarrySkillDescS4"
	},
	{
		"type":20004,
		"name":"凤求凰",
		"level":3,
		"marryLv":15,
		"addProperty":[[10,88],[16,176],[15,265]],
		"itemCount":14,
		"addPower":119,
		"icon":"S_fengqiuhuang",
		"descL":"MarrySkillDescL4",
		"descS":"MarrySkillDescS4"
	},
	{
		"type":20004,
		"name":"凤求凰",
		"level":4,
		"marryLv":20,
		"addProperty":[[10,123],[16,247],[15,371]],
		"itemCount":21,
		"addPower":130,
		"icon":"S_fengqiuhuang",
		"descL":"MarrySkillDescL4",
		"descS":"MarrySkillDescS4"
	},
	{
		"type":20004,
		"name":"凤求凰",
		"level":5,
		"marryLv":20,
		"addProperty":[[10,160],[16,321],[15,482]],
		"itemCount":29,
		"addPower":138,
		"icon":"S_fengqiuhuang",
		"descL":"MarrySkillDescL4",
		"descS":"MarrySkillDescS4"
	},
	{
		"type":20004,
		"name":"凤求凰",
		"level":6,
		"marryLv":25,
		"addProperty":[[10,201],[16,403],[15,605]],
		"itemCount":38,
		"addPower":151,
		"icon":"S_fengqiuhuang",
		"descL":"MarrySkillDescL4",
		"descS":"MarrySkillDescS4"
	},
	{
		"type":20004,
		"name":"凤求凰",
		"level":7,
		"marryLv":25,
		"addProperty":[[10,243],[16,486],[15,729]],
		"itemCount":48,
		"addPower":153,
		"icon":"S_fengqiuhuang",
		"descL":"MarrySkillDescL4",
		"descS":"MarrySkillDescS4"
	},
	{
		"type":20004,
		"name":"凤求凰",
		"level":8,
		"marryLv":30,
		"addProperty":[[10,288],[16,577],[15,866]],
		"itemCount":74,
		"addPower":168,
		"icon":"S_fengqiuhuang",
		"descL":"MarrySkillDescL4",
		"descS":"MarrySkillDescS4"
	},
	{
		"type":20004,
		"name":"凤求凰",
		"level":9,
		"marryLv":30,
		"addProperty":[[10,334],[16,668],[15,1002]],
		"itemCount":117,
		"addPower":167,
		"icon":"S_fengqiuhuang",
		"descL":"MarrySkillDescL4",
		"descS":"MarrySkillDescS4"
	},
	{
		"type":20004,
		"name":"凤求凰",
		"level":10,
		"marryLv":35,
		"addProperty":[[10,383],[16,767],[15,1151]],
		"itemCount":180,
		"addPower":184,
		"icon":"S_fengqiuhuang",
		"descL":"MarrySkillDescL4",
		"descS":"MarrySkillDescS4"
	},
	{
		"type":20004,
		"name":"凤求凰",
		"level":11,
		"marryLv":35,
		"addProperty":[[10,434],[16,868],[15,1303]],
		"itemCount":254,
		"addPower":187,
		"icon":"S_fengqiuhuang",
		"descL":"MarrySkillDescL4",
		"descS":"MarrySkillDescS4"
	},
	{
		"type":20004,
		"name":"凤求凰",
		"level":12,
		"marryLv":40,
		"addProperty":[[10,490],[16,980],[15,1470]],
		"itemCount":338,
		"addPower":206,
		"icon":"S_fengqiuhuang",
		"descL":"MarrySkillDescL4",
		"descS":"MarrySkillDescS4"
	},
	{
		"type":20004,
		"name":"凤求凰",
		"level":13,
		"marryLv":40,
		"addProperty":[[10,546],[16,1093],[15,1639]],
		"itemCount":431,
		"addPower":209,
		"icon":"S_fengqiuhuang",
		"descL":"MarrySkillDescL4",
		"descS":"MarrySkillDescS4"
	},
	{
		"type":20004,
		"name":"凤求凰",
		"level":14,
		"marryLv":45,
		"addProperty":[[10,608],[16,1217],[15,1825]],
		"itemCount":542,
		"addPower":230,
		"icon":"S_fengqiuhuang",
		"descL":"MarrySkillDescL4",
		"descS":"MarrySkillDescS4"
	},
	{
		"type":20004,
		"name":"凤求凰",
		"level":15,
		"marryLv":45,
		"addProperty":[[10,666],[16,1332],[15,1999]],
		"itemCount":680,
		"addPower":214,
		"icon":"S_fengqiuhuang",
		"descL":"MarrySkillDescL4",
		"descS":"MarrySkillDescS4"
	},
	{
		"type":20004,
		"name":"凤求凰",
		"level":16,
		"marryLv":50,
		"addProperty":[[10,730],[16,1460],[15,2190]],
		"itemCount":836,
		"addPower":236,
		"icon":"S_fengqiuhuang",
		"descL":"MarrySkillDescL4",
		"descS":"MarrySkillDescS4"
	},
	{
		"type":20004,
		"name":"凤求凰",
		"level":17,
		"marryLv":50,
		"addProperty":[[10,790],[16,1580],[15,2370]],
		"itemCount":1007,
		"addPower":222,
		"icon":"S_fengqiuhuang",
		"descL":"MarrySkillDescL4",
		"descS":"MarrySkillDescS4"
	},
	{
		"type":20004,
		"name":"凤求凰",
		"level":18,
		"marryLv":55,
		"addProperty":[[10,856],[16,1712],[15,2568]],
		"itemCount":1196,
		"addPower":244,
		"icon":"S_fengqiuhuang",
		"descL":"MarrySkillDescL4",
		"descS":"MarrySkillDescS4"
	},
	{
		"type":20004,
		"name":"凤求凰",
		"level":19,
		"marryLv":55,
		"addProperty":[[10,924],[16,1849],[15,2774]],
		"itemCount":1403,
		"addPower":253,
		"icon":"S_fengqiuhuang",
		"descL":"MarrySkillDescL4",
		"descS":"MarrySkillDescS4"
	},
	{
		"type":20004,
		"name":"凤求凰",
		"level":20,
		"marryLv":0,
		"addProperty":[[10,1000],[16,2000],[15,3000]],
		"itemCount":0,
		"addPower":279,
		"icon":"S_fengqiuhuang",
		"descL":"MarrySkillDescL4",
		"descS":"MarrySkillDescS4"
	},
	{
		"type":20005,
		"name":"白头吟",
		"level":0,
		"marryLv":10,
		"addProperty":[],
		"itemCount":2,
		"addPower":0,
		"icon":"S_baitouyin",
		"descL":"MarrySkillDescL5",
		"descS":"MarrySkillDescS5"
	},
	{
		"type":20005,
		"name":"白头吟",
		"level":1,
		"marryLv":10,
		"addProperty":[[7,92],[8,92],[9,92]],
		"itemCount":5,
		"addPower":92,
		"icon":"S_baitouyin",
		"descL":"MarrySkillDescL5",
		"descS":"MarrySkillDescS5"
	},
	{
		"type":20005,
		"name":"白头吟",
		"level":2,
		"marryLv":15,
		"addProperty":[[7,202],[8,202],[9,202]],
		"itemCount":9,
		"addPower":111,
		"icon":"S_baitouyin",
		"descL":"MarrySkillDescL5",
		"descS":"MarrySkillDescS5"
	},
	{
		"type":20005,
		"name":"白头吟",
		"level":3,
		"marryLv":15,
		"addProperty":[[7,318],[8,318],[9,318]],
		"itemCount":15,
		"addPower":115,
		"icon":"S_baitouyin",
		"descL":"MarrySkillDescL5",
		"descS":"MarrySkillDescS5"
	},
	{
		"type":20005,
		"name":"白头吟",
		"level":4,
		"marryLv":20,
		"addProperty":[[7,445],[8,445],[9,445]],
		"itemCount":23,
		"addPower":127,
		"icon":"S_baitouyin",
		"descL":"MarrySkillDescL5",
		"descS":"MarrySkillDescS5"
	},
	{
		"type":20005,
		"name":"白头吟",
		"level":5,
		"marryLv":20,
		"addProperty":[[7,579],[8,579],[9,579]],
		"itemCount":31,
		"addPower":134,
		"icon":"S_baitouyin",
		"descL":"MarrySkillDescL5",
		"descS":"MarrySkillDescS5"
	},
	{
		"type":20005,
		"name":"白头吟",
		"level":6,
		"marryLv":25,
		"addProperty":[[7,726],[8,726],[9,726]],
		"itemCount":40,
		"addPower":147,
		"icon":"S_baitouyin",
		"descL":"MarrySkillDescL5",
		"descS":"MarrySkillDescS5"
	},
	{
		"type":20005,
		"name":"白头吟",
		"level":7,
		"marryLv":25,
		"addProperty":[[7,875],[8,875],[9,875]],
		"itemCount":50,
		"addPower":149,
		"icon":"S_baitouyin",
		"descL":"MarrySkillDescL5",
		"descS":"MarrySkillDescS5"
	},
	{
		"type":20005,
		"name":"白头吟",
		"level":8,
		"marryLv":30,
		"addProperty":[[7,1039],[8,1039],[9,1039]],
		"itemCount":82,
		"addPower":164,
		"icon":"S_baitouyin",
		"descL":"MarrySkillDescL5",
		"descS":"MarrySkillDescS5"
	},
	{
		"type":20005,
		"name":"白头吟",
		"level":9,
		"marryLv":30,
		"addProperty":[[7,1202],[8,1202],[9,1202]],
		"itemCount":127,
		"addPower":163,
		"icon":"S_baitouyin",
		"descL":"MarrySkillDescL5",
		"descS":"MarrySkillDescS5"
	},
	{
		"type":20005,
		"name":"白头吟",
		"level":10,
		"marryLv":35,
		"addProperty":[[7,1381],[8,1381],[9,1381]],
		"itemCount":194,
		"addPower":179,
		"icon":"S_baitouyin",
		"descL":"MarrySkillDescL5",
		"descS":"MarrySkillDescS5"
	},
	{
		"type":20005,
		"name":"白头吟",
		"level":11,
		"marryLv":35,
		"addProperty":[[7,1564],[8,1564],[9,1564]],
		"itemCount":270,
		"addPower":182,
		"icon":"S_baitouyin",
		"descL":"MarrySkillDescL5",
		"descS":"MarrySkillDescS5"
	},
	{
		"type":20005,
		"name":"白头吟",
		"level":12,
		"marryLv":40,
		"addProperty":[[7,1764],[8,1764],[9,1764]],
		"itemCount":355,
		"addPower":200,
		"icon":"S_baitouyin",
		"descL":"MarrySkillDescL5",
		"descS":"MarrySkillDescS5"
	},
	{
		"type":20005,
		"name":"白头吟",
		"level":13,
		"marryLv":40,
		"addProperty":[[7,1967],[8,1967],[9,1967]],
		"itemCount":452,
		"addPower":203,
		"icon":"S_baitouyin",
		"descL":"MarrySkillDescL5",
		"descS":"MarrySkillDescS5"
	},
	{
		"type":20005,
		"name":"白头吟",
		"level":14,
		"marryLv":45,
		"addProperty":[[7,2190],[8,2190],[9,2190]],
		"itemCount":567,
		"addPower":223,
		"icon":"S_baitouyin",
		"descL":"MarrySkillDescL5",
		"descS":"MarrySkillDescS5"
	},
	{
		"type":20005,
		"name":"白头吟",
		"level":15,
		"marryLv":45,
		"addProperty":[[7,2399],[8,2399],[9,2399]],
		"itemCount":710,
		"addPower":208,
		"icon":"S_baitouyin",
		"descL":"MarrySkillDescL5",
		"descS":"MarrySkillDescS5"
	},
	{
		"type":20005,
		"name":"白头吟",
		"level":16,
		"marryLv":50,
		"addProperty":[[7,2628],[8,2628],[9,2628]],
		"itemCount":869,
		"addPower":229,
		"icon":"S_baitouyin",
		"descL":"MarrySkillDescL5",
		"descS":"MarrySkillDescS5"
	},
	{
		"type":20005,
		"name":"白头吟",
		"level":17,
		"marryLv":50,
		"addProperty":[[7,2844],[8,2844],[9,2844]],
		"itemCount":1044,
		"addPower":216,
		"icon":"S_baitouyin",
		"descL":"MarrySkillDescL5",
		"descS":"MarrySkillDescS5"
	},
	{
		"type":20005,
		"name":"白头吟",
		"level":18,
		"marryLv":55,
		"addProperty":[[7,3082],[8,3082],[9,3082]],
		"itemCount":1236,
		"addPower":238,
		"icon":"S_baitouyin",
		"descL":"MarrySkillDescL5",
		"descS":"MarrySkillDescS5"
	},
	{
		"type":20005,
		"name":"白头吟",
		"level":19,
		"marryLv":55,
		"addProperty":[[7,3328],[8,3328],[9,3328]],
		"itemCount":1446,
		"addPower":246,
		"icon":"S_baitouyin",
		"descL":"MarrySkillDescL5",
		"descS":"MarrySkillDescS5"
	},
	{
		"type":20005,
		"name":"白头吟",
		"level":20,
		"marryLv":0,
		"addProperty":[[7,3600],[8,3600],[9,3600]],
		"itemCount":0,
		"addPower":271,
		"icon":"S_baitouyin",
		"descL":"MarrySkillDescL5",
		"descS":"MarrySkillDescS5"
	}
]